peek/__init__.py
peek/main.py
peek_cli-0.1.3.dist-info/METADATA
peek_cli-0.1.3.dist-info/WHEEL
peek_cli-0.1.3.dist-info/entry_points.txt
peek_cli-0.1.3.dist-info/RECORD
