Metadata-Version: 2.4
Name: peek-cli
Version: 0.1.3
Summary: A lightning-fast CLI for inspecting CSVs and datasets in the terminal.
Author: Arnav Sharma
Keywords: cli,csv,data-science,eda,rich,terminal
Classifier: Environment :: Console
Classifier: Programming Language :: Python :: 3
Classifier: Topic :: Scientific/Engineering :: Information Analysis
Requires-Python: >=3.9
Requires-Dist: plotext>=5.3.2
Requires-Dist: polars>=1.36.1
Requires-Dist: rich>=14.2.0
Requires-Dist: typer>=0.21.0
Requires-Dist: vadersentiment>=3.3.2
